Workbook

Sheet Leia-me
A1: Calculadora do curso — Empresa de Assinatura de Energia Solar
A3: Como usar
A4: 1. Comece pela aba "Premissas": tarifa da sua distribuidora, tributos, desconto, taxa de administração e usina.
A5: 2. As outras abas usam essas premissas. Edite só as células amarelas com texto azul.
A6: 3. Células em preto são fórmulas; em verde, valores trazidos de outra aba. Não sobrescreva.
A8: Abas (e onde aparecem no curso)
A9: Premissas — M2 a07 / M3 a06 · Valor do crédito — M1 a07, M2 a05 e a07 · Cota e economia — M2 a06, M5 a02
A10: Unit economics — M3 a04 · Cenários Fio B — M3 a05 · Meu modelo — M3 a06 · Funil e metas — M5 a05
A11: Plano de ocupação — M6 a05 e a06 · Painel de indicadores — M10 a01 e a05
A13: Avisos importantes
A14: • Os valores iniciais são os EXEMPLOS ILUSTRATIVOS do curso (tarifa R$ 0,80/kWh sem impostos, Fio B R$ 0,20). Troque pelos da sua distribuidora (tarifas homologadas no site da ANEEL).
A15: • Fio B não compensado (GD II, Lei 14.300/2022): 2026: 60% · 2027: 75% · 2028: 90%. 2029 em diante é CENÁRIO: depende da valoração da ANEEL.
... A23: Valor trazido de outra aba

Sheet Premissas
A1: Premissas — edite aqui os números da sua distribuidora e do seu negócio
A3: Tarifa sem impostos (R$/kWh) — subgrupo que você atende
A4: TE — Tarifa de Energia | B4: 0.35
A5: TUSD — Tarifa de Uso do Sistema de Distribuição | B5: 0.45
A6: Fio B (parcela da TUSD) | B6: 0.2
A7: Tarifa sem impostos (TE + TUSD) | B7: =B4+B5 -> 0.8
A9: Tributos
A10: ICMS | B10: 0.18
A11: PIS + COFINS | B11: 0.05
A12: Tarifa com impostos (cálculo "por dentro") | B12: =IFERROR(B7/(1-(B10+B11)),0) -> 1.038961
A13: Tributos incidem sobre o valor do crédito compensado? (1 = sim, 0 = não) | B13: 1
A14: Alíquota "por dentro" aplicada ao crédito | B14: =(B10+B11)*B13 -> 0.23
A16: Transição do Fio B (GD II) — parcela NÃO compensada
A17: Ano | B17: % do Fio B pago
A18: 2026 | B18: 0.6
A19: 2027 | B19: 0.75
A20: 2028 | B20: 0.9
A21: 2029 (cenário) | B21: 1 | C21: Cenário — ajuste para testar 2029 em diante.
A23: Seu negócio
A24: Desconto ao cliente (% do valor do crédito) | B24: 0.2
A25: Taxa de administração da gestora (% do valor do crédito) | B25: 0.15
A26: Ano de referência para os cálculos (2026 a 2029) | B26: 2026
A28: Usina de referência
A29: Potência (kWp) | B29: 500
A30: Produtividade (kWh/kWp/mês) | B30: 120
A31: Geração média mensal (kWh) | B31: =B29*B30 -> 60000

Sheet Valor do crédito
A1: Valor do crédito por ano (GD II) — quanto vale 1 kWh compensado
A3: Tarifa
A4: Tarifa sem impostos | B4: =Premissas!B7 -> 0.8
A5: Tarifa com impostos | B5: =Premissas!B12 -> 1.038961
A6: Fio B (sem impostos) | B6: =Premissas!B6 -> 0.2
A8: Valor do crédito ano a ano
A9: Ano | B9: % Fio B pago | C9: Fio B pago | D9: Crédito s/ impostos | E9: Crédito c/ impostos | F9: Variação vs 2026
A10: =Premissas!A18 -> 2026 | B10: =Premissas!B18 -> 0.6 | C10: =B10*$B$6 -> 0.12 | D10: =$B$4-C10 -> 0.68 | E10: =IFERROR(D10/(1-Premissas!$B$14),0) -> 0.88311688 | F10: =IFERROR(D10/$D$10-1,0) -> 0
A11: =Premissas!A19 -> 2027 | B11: =Premissas!B19 -> 0.75 | C11: =B11*$B$6 -> 0.15 | D11: =$B$4-C11 -> 0.65 | E11: =IFERROR(D11/(1-Premissas!$B$14),0) -> 0.84415584 | F11: =IFERROR(D11/$D$10-1,0) -> -0.044117647
A12: =Premissas!A20 -> 2028 | B12: =Premissas!B20 -> 0.9 | C12: =B12*$B$6 -> 0.18 | D12: =$B$4-C12 -> 0.62 | E12: =IFERROR(D12/(1-Premissas!$B$14),0) -> 0.80519481 | F12: =IFERROR(D12/$D$10-1,0) -> -0.088235294
A13: =Premissas!A21 -> 2029 (cenário) | B13: =Premissas!B21 -> 1 | C13: =B13*$B$6 -> 0.2 | D13: =$B$4-C13 -> 0.6 | E13: =IFERROR(D13/(1-Premissas!$B$14),0) -> 0.77922078 | F13: =IFERROR(D13/$D$10-1,0) -> -0.11764706
A15: No ano de referência (usado nas outras abas)
A16: Ano de referência | B16: =Premissas!B26 -> 2026
A17: Linha do ano (1 = 2026 … 4 = 2029) | B17: =MAX(1,MIN(4,B16-2025)) -> 1
A18: Crédito sem impostos (R$/kWh) | B18: =INDEX(D10:D13,B17) -> 0.68
A19: Crédito com impostos (R$/kWh) | B19: =INDEX(E10:E13,B17) -> 0.88311688
A20: Fio B pago com impostos (R$/kWh) | B20: =IFERROR(INDEX(C10:C13,B17)/(1-(Premissas!B10+Premissas!B11)),0) -> 0.15584416
A22: Na plataforma: Configurações → Concessionárias → "Tarifa GD2" = crédito sem impostos do ano corrente (M2 aula 7).

Sheet Cota e economia
A1: Cota ideal, % de rateio e economia real do cliente (conta total)
A3: Cliente (exemplo do curso: Clínica, trifásica) | D3: Histórico | E3: Consumo (kWh)
A4: Nome do cliente | B4: Clínica (exemplo) | D4: Mês 1 | E4: 4000
A5: Tipo de ligação | B5: Trifásica | D5: Mês 2 | E5: 4000
A6: Margem de segurança da cota | B6: 0.95 | D6: Mês 3 | E6: 4000
D7: Mês 4 | E7: 4000
D8: Mês 5 | E8: 4000
D9: Mês 6 | E9: 4000
D10: Mês 7 | E10: 4000
D11: Mês 8 | E11: 4000
D12: Mês 9 | E12: 4000
D13: Mês 10 | E13: 4000
D14: Mês 11 | E14: 4000
D15: Mês 12 | E15: 4000
D16: Copie o histórico impresso na conta de luz.
A18: Cota
A19: Consumo médio mensal (12 meses) | B19: =AVERAGE(E4:E15) -> 4000 | D19: Ligação | E19: Custo disp. (kWh)
A20: Custo de disponibilidade | B20: =IFERROR(INDEX(E20:E22,MATCH(B5,D20:D22,0)),0) -> 100 | D20: Monofásica | E20: 30
A21: Cota ideal = (média − custo de disponibilidade) × margem | B21: =MAX(0,(B19-B20)*B6) -> 3705 | D21: Bifásica | E21: 50
A22: Geração média da usina | B22: =Premissas!B31 -> 60000 | D22: Trifásica | E22: 100
A23: % de rateio na usina | B23: =IFERROR(B21/B22,0) -> 0.06175
A25: Economia na conta total (ano de referência)
A26: Conta hoje (média × tarifa com impostos) | B26: =B19*Premissas!B12 -> 4155.8442
A27: Distribuidora: consumo fora da cota (no mínimo, o custo de disponibilidade) | B27: =MAX(B19-B21,B20)*Premissas!B12 -> 306.49351
A28: Distribuidora: Fio B não compensado sobre a cota | B28: =B21*'Valor do crédito'!B20 -> 577.4026
A29: Sua cobrança: cota × crédito com impostos × (1 − desconto) | B29: =B21*'Valor do crédito'!B19*(1-Premissas!B24) -> 2617.5584
A30: Total com assinatura | B30: =B27+B28+B29 -> 3501.4545
A31: Economia por mês | B31: =B26-B30 -> 654.38961
A32: Economia por ano | B32: =B31*12 -> 7852.6753
A33: Economia em % da conta total | B33: =IFERROR(B31/B26,0) -> 0.1574625
A35: O desconto é sobre a energia compensada — por isso a economia na conta total é menor que o desconto (M3 aula 4).

Sheet Unit economics
A1: Unit economics — divisão do kWh e margem por usina
A3: Divisão de 1 kWh compensado (sem impostos, ano de referência)
A4: Valor do crédito (R$/kWh) | B4: ='Valor do crédito'!B18 -> 0.68
A5: Desconto ao cliente | B5: =Premissas!B24 -> 0.2
A6: Taxa de administração | B6: =Premissas!B25 -> 0.15
A7: Cliente paga por kWh | B7: =B4*(1-B5) -> 0.544
A8: Economia do cliente por kWh | B8: =B4*B5 -> 0.136
A9: Gestora (taxa) por kWh | B9: =B4*B6 -> 0.102
A10: Repasse ao produtor por kWh | B10: =B4-B8-B9 -> 0.442
A12: Por usina, por mês (100% alocada e paga)
A13: Energia alocada (kWh/mês) | B13: =Premissas!B31 -> 60000
A14: Clientes pagam (R$/mês) | B14: =B13*B7 -> 32640
A15: Economia dos clientes (R$/mês) | B15: =B13*B8 -> 8160
A16: Taxa de administração da gestora (R$/mês) | B16: =B13*B9 -> 6120
A17: Repasse ao produtor (R$/mês) | B17: =B13*B10 -> 26520
A19: Custos variáveis da gestora
A20: Meio de pagamento (% do que os clientes pagam) | B20: 0.015
A21: Reserva de inadimplência (% do que os clientes pagam) | B21: 0.03
A22: Impostos da gestora (% da taxa) | B22: 0.1
A23: Meio de pagamento (R$/mês) | B23: =B14*B20 -> 489.6
A24: Inadimplência (R$/mês) | B24: =B14*B21 -> 979.2
A25: Impostos (R$/mês) | B25: =B16*B22 -> 612
A26: Margem de contribuição por usina (R$/mês) | B26: =B16-B23-B24-B25 -> 4039.2
A27: Margem de contribuição por kWh | B27: =IFERROR(B26/B13,0) -> 0.06732
A29: Visão do produtor (investimento na usina)
A30: Custo da usina (R$/Wp) | B30: 3.5
A31: Investimento (R$) | B31: =Premissas!B29*1000*B30 -> 1750000
A32: O&M + seguro (R$/ano) | B32: 25000
A33: Receita anual do produtor (R$) | B33: =B17*12 -> 318240
A34: Receita líquida anual (R$) | B34: =B33-B32 -> 293240
A35: Retorno simples (anos) | B35: =IFERROR(B31/B34,0) -> 5.9678079
A36: Rentabilidade anual (líquida ÷ investimento) | B36: =IFERROR(B34/B31,0) -> 0.16756571

Sheet Cenários Fio B
A1: Cenários Fio B — quem absorve a queda do crédito
A3: Política A: desconto e taxa em % do crédito (todos dividem o impacto)
A4: Ano | B4: Crédito | C4: Economia cliente | D4: Gestora | E4: Produtor
A5: ='Valor do crédito'!A10 -> 2026 | B5: ='Valor do crédito'!D10 -> 0.68 | C5: =B5*Premissas!$B$24 -> 0.136 | D5: =B5*Premissas!$B$25 -> 0.102 | E5: =B5-C5-D5 -> 0.442
A6: ='Valor do crédito'!A11 -> 2027 | B6: ='Valor do crédito'!D11 -> 0.65 | C6: =B6*Premissas!$B$24 -> 0.13 | D6: =B6*Premissas!$B$25 -> 0.0975 | E6: =B6-C6-D6 -> 0.4225
A7: ='Valor do crédito'!A12 -> 2028 | B7: ='Valor do crédito'!D12 -> 0.62 | C7: =B7*Premissas!$B$24 -> 0.124 | D7: =B7*Premissas!$B$25 -> 0.093 | E7: =B7-C7-D7 -> 0.403
A8: ='Valor do crédito'!A13 -> 2029 (cenário) | B8: ='Valor do crédito'!D13 -> 0.6 | C8: =B8*Premissas!$B$24 -> 0.12 | D8: =B8*Premissas!$B$25 -> 0.09 | E8: =B8-C8-D8 -> 0.39
A10: Política B: preço fixo por kWh ao cliente (cliente perde economia)
A11: Preço fixo cobrado (R$/kWh) | B11: =B5*(1-Premissas!B24) -> 0.544 | C11: Igual ao que o cliente paga em 2026 na política A.
A12: Ano | B12: Crédito | C12: Economia cliente | D12: Gestora | E12: Produtor
A13: =A5 -> 2026 | B13: =B5 -> 0.68 | C13: =B13-$B$11 -> 0.136 | D13: =B13*Premissas!$B$25 -> 0.102 | E13: =$B$11-D13 -> 0.442
A14: =A6 -> 2027 | B14: =B6 -> 0.65 | C14: =B14-$B$11 -> 0.106 | D14: =B14*Premissas!$B$25 -> 0.0975 | E14: =$B$11-D14 -> 0.4465
A15: =A7 -> 2028 | B15: =B7 -> 0.62 | C15: =B15-$B$11 -> 0.076 | D15: =B15*Premissas!$B$25 -> 0.093 | E15: =$B$11-D15 -> 0.451
A16: =A8 -> 2029 (cenário) | B16: =B8 -> 0.6 | C16: =B16-$B$11 -> 0.056 | D16: =B16*Premissas!$B$25 -> 0.09 | E16: =$B$11-D16 -> 0.454
A18: Economia do cliente por kWh: comparação
A19: Ano | B19: Política A | C19: Var. A | D19: Política B | E19: Var. B
A20: =A5 -> 2026 | B20: =C5 -> 0.136 | C20: =IFERROR(B20/$B$20-1,0) -> 0 | D20: =C13 -> 0.136 | E20: =IFERROR(D20/$D$20-1,0) -> 0
A21: =A6 -> 2027 | B21: =C6 -> 0.13 | C21: =IFERROR(B21/$B$20-1,0) -> -0.044117647 | D21: =C14 -> 0.106 | E21: =IFERROR(D21/$D$20-1,0) -> -0.22058824
A22: =A7 -> 2028 | B22: =C7 -> 0.124 | C22: =IFERROR(B22/$B$20-1,0) -> -0.088235294 | D22: =C15 -> 0.076 | E22: =IFERROR(D22/$D$20-1,0) -> -0.44117647
A23: =A8 -> 2029 (cenário) | B23: =C8 -> 0.12 | C23: =IFERROR(B23/$B$20-1,0) -> -0.11764706 | D23: =C16 -> 0.056 | E23: =IFERROR(D23/$D$20-1,0) -> -0.58823529
A25: Tarifa constante (cenário de estresse); reajustes costumam compensar parte da queda. Recomendação do curso: política A + cláusula de reequilíbrio.

Sheet Meu modelo
A1: Meu modelo — ponto de equilíbrio, capital de giro e projeção de 36 meses
A3: Custos fixos mensais (exemplo do curso: R$ 18.000)
A4: Operador (com encargos) | B4: 7000
A5: Vendedor — parte fixa (com encargos) | B5: 5000
A6: Plataforma | B6: 1500
A7: Contador | B7: 1500
A8: Jurídico | B8: 1000
A9: Escritório, marketing e outros | B9: 2000
A10: Total de custos fixos | B10: =SUM(B4:B9) -> 18000
A12: Premissas comerciais
A13: Cota média por cliente (kWh/mês) | B13: 500
A14: Novos clientes por mês | B14: 30
A15: Churn mensal | B15: 0.01
A16: Comissão por cliente novo (R$) | B16: 250
A17: Ano do mês 1 da operação | B17: 2026
A19: Margem e ponto de equilíbrio
A20: Custo variável sobre o que o cliente paga | B20: ='Unit economics'!B20+'Unit economics'!B21 -> 0.045
A21: Impostos sobre a taxa | B21: ='Unit economics'!B22 -> 0.1
A22: Margem de contribuição por kWh (ano de referência) | B22: ='Unit economics'!B27 -> 0.06732
A23: Ponto de equilíbrio (kWh/mês) | B23: =IFERROR(B10/B22,0) -> 267379.68
A24: Ponto de equilíbrio (clientes) | B24: =IFERROR(B23/B13,0) -> 534.75936
A25: Ponto de equilíbrio (usinas de referência) | B25: =IFERROR(B23/Premissas!B31,0) -> 4.456328
A26: Primeiro mês com resultado positivo | B26: =IFERROR(MATCH(1,L32:L67,0),"após 36 meses") -> 33
A27: Capital de giro necessário (pior saldo acumulado) | B27: =MAX(0,-MIN(K32:K67)) -> 360799.96
A29: A margem por kWh muda com o ano (transição do Fio B). Simplificação: clientes entram já pagando no mês.
D31: Mês | E31: Ano | F31: Clientes | G31: kWh alocados | H31: Margem/kWh | I31: Margem − fixos | J31: Comissões | K31: Acumulado | L31: ≥ 0?
D32: 1 | E32: =$B$17+INT((D32-1)/12) -> 2026 | F32: =$B$14 -> 30 | G32: =F32*$B$13 -> 15000 | H32: =INDEX('Valor do crédito'!$D$10:$D$13,MAX(1,MIN(4,E32-2025)))*(Premissas!$B$25-(1-Premissas!$B$24)*$B$20-Premissas!$B$25*$B$21) -> 0.06732 | I32: =G32*H32-$B$10 -> -16990.2 | J32: =$B$14*$B$16 -> 7500 | K32: =I32-J32 -> -24490.2 | L32: =IF(I32-J32>=0,1,0) -> 0
D33: 2 | E33: =$B$17+INT((D33-1)/12) -> 2026 | F33: =F32*(1-$B$15)+$B$14 -> 59.7 | G33: =F33*$B$13 -> 29850 | H33: =INDEX('Valor do crédito'!$D$10:$D$13,MAX(1,MIN(4,E33-2025)))*(Premissas!$B$25-(1-Premissas!$B$24)*$B$20-Premissas!$B$25*$B$21) -> 0.06732 | I33: =G33*H33-$B$10 -> -15990.498 | J33: =$B$14*$B$16 -> 7500 | K33: =K32+I33-J33 -> -47980.698 | L33: =IF(I33-J33>=0,1,0) -> 0
D34: 3 | E34: =$B$17+INT((D34-1)/12) -> 2026 | F34: =F33*(1-$B$15)+$B$14 -> 89.103 | G34: =F34*$B$13 -> 44551.5 | H34: =INDEX('Valor do crédito'!$D$10:$D$13,MAX(1,MIN(4,E34-2025)))*(Premissas!$B$25-(1-Premissas!$B$24)*$B$20-Premissas!$B$25*$B$21) -> 0.06732 | I34: =G34*H34-$B$10 -> -15000.793 | J34: =$B$14*$B$16 -> 7500 | K34: =K33+I34-J34 -> -70481.491 | L34: =IF(I34-J34>=0,1,0) -> 0
D35: 4 | E35: =$B$17+INT((D35-1)/12) -> 2026 | F35: =F34*(1-$B$15)+$B$14 -> 118.21197 | G35: =F35*$B$13 -> 59105.985 | H35: =INDEX('Valor do crédito'!$D$10:$D$13,MAX(1,MIN(4,E35-2025)))*(Premissas!$B$25-(1-Premissas!$B$24)*$B$20-Premissas!$B$25*$B$21) -> 0.06732 | I35: =G35*H35-$B$10 -> -14020.985 | J35: =$B$14*$B$16 -> 7500 | K35: =K34+I35-J35 -> -92002.476 | L35: =IF(I35-J35>=0,1,0) -> 0
D36: 5 | E36: =$B$17+INT((D36-1)/12) -> 2026 | F36: =F35*(1-$B$15)+$B$14 -> 147.02985 | G36: =F36*$B$13 -> 73514.925 | H36: =INDEX('Valor do crédito'!$D$10:$D$13,MAX(1,MIN(4,E36-2025)))*(Premissas!$B$25-(1-Premissas!$B$24)*$B$20-Premissas!$B$25*$B$21) -> 0.06732 | I36: =G36*H36-$B$10 -> -13050.975 | J36: =$B$14*$B$16 -> 7500 | K36: =K35+I36-J36 -> -112553.45 | L36: =IF(I36-J36>=0,1,0) -> 0
D37: 6 | E37: =$B$17+INT((D37-1)/12) -> 2026 | F37: =F36*(1-$B$15)+$B$14 -> 175.55955 | G37: =F37*$B$13 -> 87779.776 | H37: =INDEX('Valor do crédito'!$D$10:$D$13,MAX(1,MIN(4,E37-2025)))*(Premissas!$B$25-(1-Premissas!$B$24)*$B$20-Premissas!$B$25*$B$21) -> 0.06732 | I37: =G37*H37-$B$10 -> -12090.665 | J37: =$B$14*$B$16 -> 7500 | K37: =K36+I37-J37 -> -132144.12 | L37: =IF(I37-J37>=0,1,0) -> 0
D38: 7 | E38: =$B$17+INT((D38-1)/12) -> 2026 | F38: =F37*(1-$B$15)+$B$14 -> 203.80396 | G38: =F38*$B$13 -> 101901.98 | H38: =INDEX('Valor do crédito'!$D$10:$D$13,MAX(1,MIN(4,E38-2025)))*(Premissas!$B$25-(1-Premissas!$B$24)*$B$20-Premissas!$B$25*$B$21) -> 0.06732 | I38: =G38*H38-$B$10 -> -11139.959 | J38: =$B$14*$B$16 -> 7500 | K38: =K37+I38-J38 -> -150784.08 | L38: =IF(I38-J38>=0,1,0) -> 0
D39: 8 | E39: =$B$17+INT((D39-1)/12) -> 2026 | F39: =F38*(1-$B$15)+$B$14 -> 231.76592 | G39: =F39*$B$13 -> 115882.96 | H39: =INDEX('Valor do crédito'!$D$10:$D$13,MAX(1,MIN(4,E39-2025)))*(Premissas!$B$25-(1-Premissas!$B$24)*$B$20-Premissas!$B$25*$B$21) -> 0.06732 | I39: =G39*H39-$B$10 -> -10198.759 | J39: =$B$14*$B$16 -> 7500 | K39: =K38+I39-J39 -> -168482.83 | L39: =IF(I39-J39>=0,1,0) -> 0
D40: 9 | E40: =$B$17+INT((D40-1)/12) -> 2026 | F40: =F39*(1-$B$15)+$B$14 -> 259.44826 | G40: =F40*$B$13 -> 129724.13 | H40: =INDEX('Valor do crédito'!$D$10:$D$13,MAX(1,MIN(4,E40-2025)))*(Premissas!$B$25-(1-Premissas!$B$24)*$B$20-Premissas!$B$25*$B$21) -> 0.06732 | I40: =G40*H40-$B$10 -> -9266.9717 | J40: =$B$14*$B$16 -> 7500 | K40: =K39+I40-J40 -> -185249.81 | L40: =IF(I40-J40>=0,1,0) -> 0
D41: 10 | E41: =$B$17+INT((D41-1)/12) -> 2026 | F41: =F40*(1-$B$15)+$B$14 -> 286.85377 | G41: =F41*$B$13 -> 143426.89 | H41: =INDEX('Valor do crédito'!$D$10:$D$13,MAX(1,MIN(4,E41-2025)))*(Premissas!$B$25-(1-Premissas!$B$24)*$B$20-Premissas!$B$25*$B$21) -> 0.06732 | I41: =G41*H41-$B$10 -> -8344.5019 | J41: =$B$14*$B$16 -> 7500 | K41: =K40+I41-J41 -> -201094.31 | L41: =IF(I41-J41>=0,1,0) -> 0
D42: 11 | E42: =$B$17+INT((D42-1)/12) -> 2026 | F42: =F41*(1-$B$15)+$B$14 -> 313.98524 | G42: =F42*$B$13 -> 156992.62 | H42: =INDEX('Valor do crédito'!$D$10:$D$13,MAX(1,MIN(4,E42-2025)))*(Premissas!$B$25-(1-Premissas!$B$24)*$B$20-Premissas!$B$25*$B$21) -> 0.06732 | I42: =G42*H42-$B$10 -> -7431.2569 | J42: =$B$14*$B$16 -> 7500 | K42: =K41+I42-J42 -> -216025.57 | L42: =IF(I42-J42>=0,1,0) -> 0
D43: 12 | E43: =$B$17+INT((D43-1)/12) -> 2026 | F43: =F42*(1-$B$15)+$B$14 -> 340.84538 | G43: =F43*$B$13 -> 170422.69 | H43: =INDEX('Valor do crédito'!$D$10:$D$13,MAX(1,MIN(4,E43-2025)))*(Premissas!$B$25-(1-Premissas!$B$24)*$B$20-Premissas!$B$25*$B$21) -> 0.06732 | I43: =G43*H43-$B$10 -> -6527.1443 | J43: =$B$14*$B$16 -> 7500 | K43: =K42+I43-J43 -> -230052.71 | L43: =IF(I43-J43>=0,1,0) -> 0
D44: 13 | E44: =$B$17+INT((D44-1)/12) -> 2027 | F44: =F43*(1-$B$15)+$B$14 -> 367.43693 | G44: =F44*$B$13 -> 183718.47 | H44: =INDEX('Valor do crédito'!$D$10:$D$13,MAX(1,MIN(4,E44-2025)))*(Premissas!$B$25-(1-Premissas!$B$24)*$B$20-Premissas!$B$25*$B$21) -> 0.06435 | I44: =G44*H44-$B$10 -> -6177.7167 | J44: =$B$14*$B$16 -> 7500 | K44: =K43+I44-J44 -> -243730.43 | L44: =IF(I44-J44>=0,1,0) -> 0
... D67: 36 | E67: =$B$17+INT((D67-1)/12) -> 2028 | F67: =F66*(1-$B$15)+$B$14 -> 910.76035 | G67: =F67*$B$13 -> 455380.17 | H67: =INDEX('Valor do crédito'!$D$10:$D$13,MAX(1,MIN(4,E67-2025)))*(Premissas!$B$25-(1-Premissas!$B$24)*$B$20-Premissas!$B$25*$B$21) -> 0.06138 | I67: =G67*H67-$B$10 -> 9951.235 | J67: =$B$14*$B$16 -> 7500 | K67: =K66+I67-J67 -> -354907.24 | L67: =IF(I67-J67>=0,1,0) -> 1

Sheet Funil e metas
A1: Funil e metas comerciais
A3: Conversões (exemplos ilustrativos — meça as suas)
A4: Lead → conta de luz recebida | B4: 0.5
A5: Conta → proposta apresentada | B5: 0.8
A6: Proposta → aceite | B6: 0.4
A7: Aceite → contrato e documentos | B7: 0.9
A8: Contrato → 1ª cobrança paga | B8: 0.95
A9: Conversão total lead → cliente pagante | B9: =PRODUCT(B4:B8) -> 0.1368
A11: Meta
A12: Novos clientes pagantes por mês | B12: ='Meu modelo'!B14 -> 30
A13: Leads necessários por mês | B13: =IFERROR(ROUNDUP(B12/B9,0),0) -> 220
A14: Propostas a apresentar por mês | B14: =IFERROR(ROUNDUP(B12/(B6*B7*B8),0),0) -> 88
A15: Clientes que um consultor fecha por mês | B15: 6
A16: Consultores necessários | B16: =IFERROR(ROUNDUP(B12/B15,0),0) -> 5
A17: Meses até o ponto de equilíbrio em clientes (sem churn) | B17: =IFERROR('Meu modelo'!B24/B12,0) -> 17.825312

Sheet Plano de ocupação
A1: Plano de ocupação da usina e planilha de rateio
A3: Energia disponível da usina (kWh/mês) | B3: =Premissas!B31 -> 60000
A4: Margem de segurança da cota | B4: 0.95
A6: Cliente | B6: UC | C6: Ligação | D6: Consumo médio | E6: Cota (kWh) | F6: % rateio
A7: Padaria | C7: Trifásica | D7: 2500 | E7: =IF(D7="","",MAX(0,(D7-IF(C7="Trifásica",100,IF(C7="Bifásica",50,30)))*$B$4)) -> 2280 | F7: =IF(E7="","",IFERROR(E7/$B$3,0)) -> 0.038
A8: Clínica | C8: Trifásica | D8: 4000 | E8: =IF(D8="","",MAX(0,(D8-IF(C8="Trifásica",100,IF(C8="Bifásica",50,30)))*$B$4)) -> 3705 | F8: =IF(E8="","",IFERROR(E8/$B$3,0)) -> 0.06175
A9: Academia | C9: Trifásica | D9: 6200 | E9: =IF(D9="","",MAX(0,(D9-IF(C9="Trifásica",100,IF(C9="Bifásica",50,30)))*$B$4)) -> 5795 | F9: =IF(E9="","",IFERROR(E9/$B$3,0)) -> 0.096583333
A10: Restaurante | C10: Trifásica | D10: 3800 | E10: =IF(D10="","",MAX(0,(D10-IF(C10="Trifásica",100,IF(C10="Bifásica",50,30)))*$B$4)) -> 3515 | F10: =IF(E10="","",IFERROR(E10/$B$3,0)) -> 0.058583333
A11: Farmácia | C11: Trifásica | D11: 2200 | E11: =IF(D11="","",MAX(0,(D11-IF(C11="Trifásica",100,IF(C11="Bifásica",50,30)))*$B$4)) -> 1995 | F11: =IF(E11="","",IFERROR(E11/$B$3,0)) -> 0.03325
A12: Escola | C12: Trifásica | D12: 5200 | E12: =IF(D12="","",MAX(0,(D12-IF(C12="Trifásica",100,IF(C12="Bifásica",50,30)))*$B$4)) -> 4845 | F12: =IF(E12="","",IFERROR(E12/$B$3,0)) -> 0.08075
A13: Mercado | C13: Trifásica | D13: 9000 | E13: =IF(D13="","",MAX(0,(D13-IF(C13="Trifásica",100,IF(C13="Bifásica",50,30)))*$B$4)) -> 8455 | F13: =IF(E13="","",IFERROR(E13/$B$3,0)) -> 0.14091667
A14: Pousada | C14: Trifásica | D14: 3200 | E14: =IF(D14="","",MAX(0,(D14-IF(C14="Trifásica",100,IF(C14="Bifásica",50,30)))*$B$4)) -> 2945 | F14: =IF(E14="","",IFERROR(E14/$B$3,0)) -> 0.049083333
A15: Escritório | C15: Bifásica | D15: 1400 | E15: =IF(D15="","",MAX(0,(D15-IF(C15="Trifásica",100,IF(C15="Bifásica",50,30)))*$B$4)) -> 1282.5 | F15: =IF(E15="","",IFERROR(E15/$B$3,0)) -> 0.021375
A16: Residência 1 | C16: Bifásica | D16: 450 | E16: =IF(D16="","",MAX(0,(D16-IF(C16="Trifásica",100,IF(C16="Bifásica",50,30)))*$B$4)) -> 380 | F16: =IF(E16="","",IFERROR(E16/$B$3,0)) -> 0.0063333333
A17: Residência 2 | C17: Bifásica | D17: 600 | E17: =IF(D17="","",MAX(0,(D17-IF(C17="Trifásica",100,IF(C17="Bifásica",50,30)))*$B$4)) -> 522.5 | F17: =IF(E17="","",IFERROR(E17/$B$3,0)) -> 0.0087083333
A18: Residência 3 | C18: Bifásica | D18: 520 | E18: =IF(D18="","",MAX(0,(D18-IF(C18="Trifásica",100,IF(C18="Bifásica",50,30)))*$B$4)) -> 446.5 | F18: =IF(E18="","",IFERROR(E18/$B$3,0)) -> 0.0074416667
... A21: Residência 6 | C21: Bifásica | D21: 900 | E21: =IF(D21="","",MAX(0,(D21-IF(C21="Trifásica",100,IF(C21="Bifásica",50,30)))*$B$4)) -> 807.5 | F21: =IF(E21="","",IFERROR(E21/$B$3,0)) -> 0.013458333
E22: =IF(D22="","",MAX(0,(D22-IF(C22="Trifásica",100,IF(C22="Bifásica",50,30)))*$B$4)) | F22: =IF(E22="","",IFERROR(E22/$B$3,0))
E23: =IF(D23="","",MAX(0,(D23-IF(C23="Trifásica",100,IF(C23="Bifásica",50,30)))*$B$4)) | F23: =IF(E23="","",IFERROR(E23/$B$3,0))
E24: =IF(D24="","",MAX(0,(D24-IF(C24="Trifásica",100,IF(C24="Bifásica",50,30)))*$B$4)) | F24: =IF(E24="","",IFERROR(E24/$B$3,0))
E25: =IF(D25="","",MAX(0,(D25-IF(C25="Trifásica",100,IF(C25="Bifásica",50,30)))*$B$4)) | F25: =IF(E25="","",IFERROR(E25/$B$3,0))
E26: =IF(D26="","",MAX(0,(D26-IF(C26="Trifásica",100,IF(C26="Bifásica",50,30)))*$B$4)) | F26: =IF(E26="","",IFERROR(E26/$B$3,0))
E27: =IF(D27="","",MAX(0,(D27-IF(C27="Trifásica",100,IF(C27="Bifásica",50,30)))*$B$4)) | F27: =IF(E27="","",IFERROR(E27/$B$3,0))
E28: =IF(D28="","",MAX(0,(D28-IF(C28="Trifásica",100,IF(C28="Bifásica",50,30)))*$B$4)) | F28: =IF(E28="","",IFERROR(E28/$B$3,0))
E29: =IF(D29="","",MAX(0,(D29-IF(C29="Trifásica",100,IF(C29="Bifásica",50,30)))*$B$4)) | F29: =IF(E29="","",IFERROR(E29/$B$3,0))
E30: =IF(D30="","",MAX(0,(D30-IF(C30="Trifásica",100,IF(C30="Bifásica",50,30)))*$B$4)) | F30: =IF(E30="","",IFERROR(E30/$B$3,0))
E31: =IF(D31="","",MAX(0,(D31-IF(C31="Trifásica",100,IF(C31="Bifásica",50,30)))*$B$4)) | F31: =IF(E31="","",IFERROR(E31/$B$3,0))
E32: =IF(D32="","",MAX(0,(D32-IF(C32="Trifásica",100,IF(C32="Bifásica",50,30)))*$B$4)) | F32: =IF(E32="","",IFERROR(E32/$B$3,0))
E33: =IF(D33="","",MAX(0,(D33-IF(C33="Trifásica",100,IF(C33="Bifásica",50,30)))*$B$4)) | F33: =IF(E33="","",IFERROR(E33/$B$3,0))
... E36: =IF(D36="","",MAX(0,(D36-IF(C36="Trifásica",100,IF(C36="Bifásica",50,30)))*$B$4)) | F36: =IF(E36="","",IFERROR(E36/$B$3,0))
A38: Total alocado (kWh) | E38: =SUM(E7:E36) -> 37943
A39: Ocupação da usina | E39: =IFERROR(E38/B3,0) -> 0.63238333
A40: Maior participação de um cliente | E40: =IFERROR(MAX(F7:F36),0) -> 0.14091667
A41: Saldo para vender (kWh) | E41: =B3-E38 -> 22057
A42: Ocupação entre 90% e 98%? | E42: =IF(AND(E39>=0.9,E39<=0.98),"OK","AJUSTAR") -> AJUSTAR
A43: Nenhum cliente com 25% ou mais? | E43: =IF(E40<0.25,"OK","RISCO GD III") -> OK
A45: Com a lista de exemplo a usina fica em ~63%: acrescente clientes até chegar a 90–98% (exercício do M6 aula 6). Na plataforma, vínculo acima do saldo é recusado.

Sheet Painel de indicadores
A1: Painel de indicadores — 12 indicadores, meta e semáforo (M10)
A3: Indicador | B3: Meta | C3: Sentido | D3: Mês 1 | E3: Mês 2 | F3: Mês 3 | G3: Mês 3
A4: 1. Taxa de ocupação (alocada ÷ disponível) | B4: 0.9 | C4: >= | D4: 0.91 | E4: 0.94 | F4: 0.95 | G4: =IF(F4="","",IF(IF(C4=">=",F4>=B4,F4<=B4),"verde","vermelho")) -> verde
A5: 2. Desempenho de geração (gerada ÷ esperada) | B5: 0.95 | C5: >= | D5: 0.97 | E5: 0.92 | F5: 0.99 | G5: =IF(F5="","",IF(IF(C5=">=",F5>=B5,F5<=B5),"verde","vermelho")) -> verde
A6: 3. Energia compensada ÷ alocada | B6: 0.95 | C6: >= | D6: 0.9 | E6: 0.96 | F6: 0.97 | G6: =IF(F6="","",IF(IF(C6=">=",F6>=B6,F6<=B6),"verde","vermelho")) -> verde
A7: 4. Novos clientes no mês | B7: 30 | C7: >= | D7: 18 | E7: 26 | F7: 31 | G7: =IF(F7="","",IF(IF(C7=">=",F7>=B7,F7<=B7),"verde","vermelho")) -> verde
A8: 5. Conversão proposta → cliente pagante | B8: 0.25 | C8: >= | D8: 0.22 | E8: 0.27 | F8: 0.3 | G8: =IF(F8="","",IF(IF(C8=">=",F8>=B8,F8<=B8),"verde","vermelho")) -> verde
A9: 6. CAC (R$ por cliente) | B9: 400 | C9: <= | D9: 520 | E9: 450 | F9: 390 | G9: =IF(F9="","",IF(IF(C9=">=",F9>=B9,F9<=B9),"verde","vermelho")) -> verde
A10: 7. Receita da gestora (R$/mês) | B10: 6000 | C10: >= | D10: 3100 | E10: 4800 | F10: 6200 | G10: =IF(F10="","",IF(IF(C10=">=",F10>=B10,F10<=B10),"verde","vermelho")) -> verde
A11: 8. Taxa de recebimento (recebido ÷ faturado) | B11: 0.95 | C11: >= | D11: 0.89 | E11: 0.93 | F11: 0.96 | G11: =IF(F11="","",IF(IF(C11=">=",F11>=B11,F11<=B11),"verde","vermelho")) -> verde
A12: 9. Inadimplência > 30 dias (% do faturado) | B12: 0.03 | C12: <= | D12: 0 | E12: 0.025 | F12: 0.031 | G12: =IF(F12="","",IF(IF(C12=">=",F12>=B12,F12<=B12),"verde","vermelho")) -> vermelho
A13: 10. Resultado do mês (R$) | B13: 0 | C13: >= | D13: -14000 | E13: -9000 | F13: -2500 | G13: =IF(F13="","",IF(IF(C13=">=",F13>=B13,F13<=B13),"verde","vermelho")) -> vermelho
A14: 11. Churn mensal | B14: 0.01 | C14: <= | D14: 0 | E14: 0.007 | F14: 0.012 | G14: =IF(F14="","",IF(IF(C14=">=",F14>=B14,F14<=B14),"verde","vermelho")) -> vermelho
A15: 12. Economia média por cliente (R$/mês) | B15: 150 | C15: >= | D15: 165 | E15: 160 | F15: 158 | G15: =IF(F15="","",IF(IF(C15=">=",F15>=B15,F15<=B15),"verde","vermelho")) -> verde
A17: Valores de exemplo — substitua pelos do seu laboratório ou da sua empresa. Metas são referências de gestão do curso.
A19: Comentário do mês (o que foi bem, o que foi mal, o que fazer):
A20: Escreva aqui…
